<Properties StartupConfiguration="{EDB88F39-2CE6-4DB6-904D-91A8199E344B}|Default">
  <MonoDevelop.Ide.Workbench />
  <MonoDevelop.Ide.ItemProperties.Phonebook.iOS FirstBuild="True" PreferredExecutionTarget="MonoDevelop.IPhone.IPhoneSimulatorTarget.">
    <MonoDevelop.MacDev.AppleDevelopmentTeam />
  </MonoDevelop.Ide.ItemProperties.Phonebook.iOS>
  <MonoDevelop.Ide.DebuggingService.PinnedWatches />
  <MonoDevelop.Ide.Workspace ActiveConfiguration="Debug" />
  <MonoDevelop.Ide.DebuggingService.Breakpoints>
    <BreakpointStore />
  </MonoDevelop.Ide.DebuggingService.Breakpoints>
  <MultiItemStartupConfigurations />
  <MonoDevelop.Ide.ItemProperties.Phonebook.Droid PreferredExecutionTarget="Android.Android_Accelerated_Oreo" />
</Properties>